nonebot_plugin_simple_setu/__init__.py
nonebot_plugin_simple_setu/config.py
nonebot_plugin_simple_setu-0.1.30.dist-info/licenses/LICENSE
nonebot_plugin_simple_setu-0.1.30.dist-info/METADATA
nonebot_plugin_simple_setu-0.1.30.dist-info/WHEEL
nonebot_plugin_simple_setu-0.1.30.dist-info/top_level.txt
nonebot_plugin_simple_setu-0.1.30.dist-info/RECORD
