Metadata-Version: 2.4
Name: nonebot-plugin-simple-setu
Version: 0.1.30
Summary: 一个简单到不能再简单的色图插件
Author-email: nomdn <iduhih777@outlook.com>
License: GNU LESSER GENERAL PUBLIC LICENSE
Project-URL: homepage, https://github.com/nomdn/nonebot-plugin-simple-setu
Project-URL: repository, https://github.com/nomdn/nonebot-plugin-simple-setu
Project-URL: documentation, https://github.com/nomdn/nonebot-plugin-simple-setu
Keywords: nonebot2,plugin,setu,image,pixiv
Classifier: Development Status :: 3 - Alpha
Classifier: Intended Audience :: Developers
Classifier: License :: OSI Approved :: GNU Lesser General Public License v3 (LGPLv3)
Classifier: Programming Language :: Python :: 3
Classifier: Programming Language :: Python :: 3.8
Classifier: Programming Language :: Python :: 3.9
Classifier: Programming Language :: Python :: 3.10
Classifier: Topic :: Software Development :: Libraries :: Python Modules
Classifier: Topic :: Utilities
Requires-Python: >=3.8
License-File: LICENSE
Requires-Dist: nonebot2<3.0.0,>=2.3.0
Requires-Dist: nonebot-adapter-onebot>=2.0.0
Requires-Dist: httpx>=0.28.1
Provides-Extra: dev
Requires-Dist: pytest; extra == "dev"
Requires-Dist: black; extra == "dev"
Requires-Dist: flake8; extra == "dev"
Requires-Dist: isort; extra == "dev"
Dynamic: license-file
